burningkeys/__init__.py
burningkeys/__main__.py
burningkeys/example_config.py
burningkeys/execute_config.py
burningkeys/read_config.py
burningkeys-2024.12.9.dist-info/METADATA
burningkeys-2024.12.9.dist-info/WHEEL
burningkeys-2024.12.9.dist-info/entry_points.txt
burningkeys-2024.12.9.dist-info/licenses/LICENSE
burningkeys-2024.12.9.dist-info/RECORD
