Metadata-Version: 2.3
Name: Burningkeys
Version: 2024.12.9
Summary: Turns any text any editor into a super customisable editor (by allowing to set global hotkeys)
Author: Günthner
Keywords: Coding,Hotkeys,Vim
Classifier: Environment :: Console
Classifier: License :: OSI Approved :: MIT License
Classifier: Operating System :: OS Independent
Classifier: Programming Language :: Python :: 3
Requires-Python: >=3.8
Requires-Dist: keyboard>=0.13.0
